sidecar/__init__.py
sidecar/_frontend.py
sidecar/_version.py
sidecar/sidecar.py
sidecar-0.8.0.data/data/share/jupyter/labextensions/@jupyter-widgets/jupyterlab-sidecar/package.json
sidecar-0.8.0.data/data/share/jupyter/labextensions/@jupyter-widgets/jupyterlab-sidecar/static/744.f041d4110f09d9fe967e.js
sidecar-0.8.0.data/data/share/jupyter/labextensions/@jupyter-widgets/jupyterlab-sidecar/static/747.0060f8fbdb6e7670d41e.js
sidecar-0.8.0.data/data/share/jupyter/labextensions/@jupyter-widgets/jupyterlab-sidecar/static/remoteEntry.dd57cee6d068fe4034db.js
sidecar-0.8.0.data/data/share/jupyter/labextensions/@jupyter-widgets/jupyterlab-sidecar/static/style.js
sidecar-0.8.0.data/data/share/jupyter/labextensions/@jupyter-widgets/jupyterlab-sidecar/static/third-party-licenses.json
sidecar-0.8.0.data/data/share/jupyter/labextensions/@jupyter-widgets/jupyterlab-sidecar/install.json
sidecar-0.8.0.dist-info/METADATA
sidecar-0.8.0.dist-info/WHEEL
sidecar-0.8.0.dist-info/licenses/LICENSE
sidecar-0.8.0.dist-info/licenses/LICENSE.txt
sidecar-0.8.0.dist-info/RECORD
