Metadata-Version: 2.4
Name: sidecar
Version: 0.8.0
Dynamic: Keywords
Summary: A sidecar output widget for JupyterLab
Project-URL: Homepage, https://github.com/jupyter-widgets/jupyterlab-sidecar
Project-URL: Bug Tracker, https://github.com/jupyter-widgets/jupyterlab-sidecar/issues
Project-URL: Repository, https://github.com/jupyter-widgets/jupyterlab-sidecar
Author-email: Project Jupyter <ipython-dev@scipy.org>
License: BSD 3-Clause License
License-File: LICENSE
License-File: LICENSE.txt
Classifier: Framework :: Jupyter
Classifier: Framework :: Jupyter :: JupyterLab
Classifier: Framework :: Jupyter :: JupyterLab :: 4
Classifier: Framework :: Jupyter :: JupyterLab :: Extensions
Classifier: Framework :: Jupyter :: JupyterLab :: Extensions :: Prebuilt
Classifier: License :: OSI Approved :: BSD License
Classifier: Programming Language :: Python
Classifier: Programming Language :: Python :: 3
Classifier: Programming Language :: Python :: 3.8
Classifier: Programming Language :: Python :: 3.9
Classifier: Programming Language :: Python :: 3.10
Classifier: Programming Language :: Python :: 3.11
Requires-Python: >=3.8
Requires-Dist: ipywidgets<9,>=8
